<!DOCTYPE service-builder PUBLIC "-//Liferay//DTD Service Builder 6.2.0//EN" "http://www.liferay.com/dtd/liferay-service-builder_6_2_0.dtd">

<service-builder package-path="com.dasannetworks.vn.sb">
	<namespace>tms</namespace>

	<entity name="Device" local-service="true" cache-enabled="false">
		<!-- PK fields -->

		<column name="deviceId" type="long" primary="true"></column>

		<!-- Group instance -->

		<column name="groupId" type="long"></column>

		<!-- Audit fields -->

		<column name="companyId" type="long"></column>
		<column name="userId" type="long"></column>
		<column name="userName" type="String"></column>
		<column name="createDate" type="Date"></column>
		<column name="modifiedDate" type="Date"></column>

		<!-- Other fields -->

		<column name="modelName" type="String"></column>
		<column name="serialNumber" type="String"></column>
		<column name="hardwareRevision" type="String"></column>
		<column name="softwareRevision" type="String"></column>
		<column name="manufacturerSerial" type="String"></column>
		<column name="macAddress" type="String"></column>
		<column name="partNumber" type="String"></column>
		<column name="specification" type="String"></column>
		<column name="factoryOut" type="Date"></column>
		<column name="warrantyStartDate" type="Date"></column>
		<column name="warrantyEndDate" type="Date"></column>

		<!-- Purchase Order -->
		<column name="purchaseOrderId" type="long"></column>

		<!-- Finder methods -->

		<finder name="PurchaseOrderId" return-type="Collection">
			<finder-column name="purchaseOrderId" />
		</finder>

		<finder name="SerialNumber" return-type="Device" unique="true">
			<finder-column name="serialNumber" />
		</finder>
		
		<finder name="CheckWarrantyInfo" return-type="Collection">
			<finder-column name="serialNumber" />
			<finder-column name="macAddress" />
		</finder>
		
	</entity>

	<entity name="PurchaseOrder" local-service="true" cache-enabled="false">
		<!-- PK fields -->

		<column name="purchaseOrderId" type="long" primary="true"></column>

		<!-- Audit fields -->

		<column name="companyId" type="long"></column>
		<column name="userId" type="long"></column>
		<column name="userName" type="String"></column>
		<column name="createDate" type="Date"></column>
		<column name="modifiedDate" type="Date"></column>

		<column name="customer" type="String"></column>
		<column name="signDate" type="Date"></column>
		<column name="purchaseOrderNumber" type="String"></column>

		<finder name="PurchaseOrderNumber" return-type="PurchaseOrder"
			unique="true">
			<finder-column name="purchaseOrderNumber" />
		</finder>
	</entity>

	<entity name="HandOverForm" local-service="true" cache-enabled="false">
		<!-- PK fields -->

		<column name="handOverFormId" type="long" primary="true"></column>

		<!-- Audit fields -->

		<column name="companyId" type="long"></column>
		<column name="userId" type="long"></column>
		<column name="userName" type="String"></column>
		<column name="createDate" type="Date"></column>
		<column name="modifiedDate" type="Date"></column>

		<column name="customerCode" type="String"></column>
		<column name="contactPoint" type="String"></column>
		<column name="email" type="String"></column>
		<column name="phone" type="String"></column>
		<column name="location" type="String"></column>
		<column name="personInCharge" type="String"></column>
		<column name="handOverFormNumber" type="String"></column>
		<column name="note" type="String"></column>
		<column name="assignDate" type="Date"></column>
		<column name="estimatedReturnDate" type="Date"></column>

		<finder name="HandOverFormNumber" return-type="HandOverForm"
				unique="true">
			<finder-column name="handOverFormNumber" />
		</finder>
	</entity>

	<entity name="HandOverDevice">
		<!-- PK fields -->

		<column name="handOverFormId" type="long" primary="true"></column>
		<column name="deviceId" type="long" primary="true"></column>

		<!-- Audit fields -->

		<column name="companyId" type="long"></column>
		<column name="userId" type="long"></column>
		<column name="userName" type="String"></column>
		<column name="createDate" type="Date"></column>
		<column name="modifiedDate" type="Date"></column>

		<column name="faultNote" type="String"></column>
		<column name="status" type="String"></column>

		<!-- Finder methods -->

		<finder name="HandOverFormId" return-type="Collection">
			<finder-column name="handOverFormId" />
		</finder>

		<finder name="DeviceId" return-type="Device" unique="true">
			<finder-column name="deviceId" />
		</finder>
	</entity>

	<entity name="Contact" uuid="true" local-service="true" cache-enabled="false">
		<!-- PK fields -->

		<column name="id" type="long" primary="true" ></column>

		<!-- Audit fields -->

		<column name="firstname" type="String" ></column>
		<column name="lastname" type="String" ></column>
		<column name="telephone" type="String" ></column>
		<column name="email" type="String"></column>
	</entity>

</service-builder>